outliers_antuanant
