Metadata-Version: 2.1
Name: outliers-antuanant
Version: 0.0.2
Summary: Technique for Outliers Removal
Home-page: https://github.com/Anant99-sys/outliers
Author: Anant Chopra
Author-email: anantchopra95@gmail.com
License: UNKNOWN
Platform: UNKNOWN
Classifier: Programming Language :: Python :: 3
Classifier: License :: OSI Approved :: MIT License
Classifier: Operating System :: OS Independent
Requires-Python: >=3.7
